cooodecooo/LICENSE
cooodecooo/README.md
cooodecooo/__init__.py
cooodecooo/requirements.txt
cooodecooo/thirdparty.json
cooodecooo-0.10.dist-info/LICENSE.rst
cooodecooo-0.10.dist-info/METADATA
cooodecooo-0.10.dist-info/WHEEL
cooodecooo-0.10.dist-info/top_level.txt
cooodecooo-0.10.dist-info/RECORD
