Metadata-Version: 2.1
Name: cooodecooo
Version: 0.10
Summary: A decorator that compiles C/C++ functions with Clang in Python
Home-page: https://github.com/hansalemaos/cooodecooo
Author: Johannes Fischer
Author-email: aulasparticularesdealemaosp@gmail.com
License: MIT
Keywords: c++,c,compile,decorator
Classifier: Development Status :: 4 - Beta
Classifier: Programming Language :: Python :: 3 :: Only
Classifier: Programming Language :: Python :: 3.10
Classifier: Topic :: Software Development :: Libraries :: Python Modules
Classifier: Topic :: Utilities
License-File: LICENSE.rst
Requires-Dist: flatten-any-dict-iterable-or-whatsoever
Requires-Dist: more-itertools
Requires-Dist: numpy
Requires-Dist: pandas
